walletrpcs/__init__.py
walletrpcs/rpcs.py
walletrpcs-0.1.2.dist-info/METADATA
walletrpcs-0.1.2.dist-info/WHEEL
walletrpcs-0.1.2.dist-info/top_level.txt
walletrpcs-0.1.2.dist-info/RECORD
