Metadata-Version: 2.1
Name: walletrpcs
Version: 0.1.2
Summary: web socket for web3
Home-page: https://github.com/username/my_package
Author: simson
Classifier: Programming Language :: Python :: 3
Classifier: License :: OSI Approved :: MIT License
Classifier: Operating System :: OS Independent
Requires-Python: >=3.6
